[{"c_id": 134, "name": "Bamako", "state_code": "BKO", "cities": [{"id": 67587, "name": "Bamako"}]}, {"c_id": 134, "name": "Gao Region", "state_code": "7", "cities": [{"id": 67584, "name": "Ansongo"}, {"id": 67592, "name": "Cercle de Bourem"}, {"id": 67601, "name": "Gao"}, {"id": 67602, "name": "Gao Cercle"}, {"id": 67605, "name": "In\u00e9kar"}]}, {"c_id": 134, "name": "Kayes Region", "state_code": "1", "cities": [{"id": 67586, "name": "Bafoulab\u00e9"}, {"id": 67608, "name": "Kayes"}, {"id": 67611, "name": "Kita"}, {"id": 67612, "name": "Kokofata"}, {"id": 67623, "name": "Sagalo"}]}, {"c_id": 134, "name": "Kidal Region", "state_code": "8", "cities": [{"id": 67583, "name": "Abe\u00efbara"}, {"id": 67595, "name": "Cercle d\u2019Abe\u00efbara"}, {"id": 67609, "name": "Kidal"}]}, {"c_id": 134, "name": "Koulikoro Region", "state_code": "2", "cities": [{"id": 67588, "name": "Banamba"}, {"id": 67606, "name": "Kangaba"}, {"id": 67607, "name": "Kati"}, {"id": 67613, "name": "Kolokani"}, {"id": 67615, "name": "Koulikoro"}]}, {"c_id": 134, "name": "M\u00e9naka Region", "state_code": "9", "cities": []}, {"c_id": 134, "name": "Mopti Region", "state_code": "5", "cities": [{"id": 67589, "name": "Bandiagara"}, {"id": 67598, "name": "Dj\u00e9nn\u00e9"}, {"id": 67599, "name": "Douentza"}, {"id": 67600, "name": "Douentza Cercle"}, {"id": 67620, "name": "Mopti"}, {"id": 67629, "name": "T\u00e9nenkou"}]}, {"c_id": 134, "name": "S\u00e9gou Region", "state_code": "4", "cities": [{"id": 67590, "name": "Baroueli"}, {"id": 67594, "name": "Cercle de San"}, {"id": 67618, "name": "K\u00e9-Macina"}, {"id": 67610, "name": "Kinmparana"}, {"id": 67619, "name": "Markala"}, {"id": 67624, "name": "San"}, {"id": 67627, "name": "S\u00e9gou"}, {"id": 67626, "name": "Sokolo"}]}, {"c_id": 134, "name": "Sikasso Region", "state_code": "3", "cities": [{"id": 67591, "name": "Bougouni"}, {"id": 67614, "name": "Kolondi\u00e9ba"}, {"id": 67616, "name": "Koutiala"}, {"id": 67617, "name": "Koutiala Cercle"}, {"id": 67622, "name": "Ntossoni"}, {"id": 67625, "name": "Sikasso"}, {"id": 67630, "name": "Yorosso"}]}, {"c_id": 134, "name": "Taoud\u00e9nit Region", "state_code": "10", "cities": []}, {"c_id": 134, "name": "Tombouctou Region", "state_code": "6", "cities": [{"id": 67585, "name": "Araouane"}, {"id": 67593, "name": "Cercle de Goundam"}, {"id": 67596, "name": "Dire"}, {"id": 67603, "name": "Goundam"}, {"id": 67604, "name": "Gourma-Rharous Cercle"}, {"id": 67621, "name": "Niafunk\u00e9"}, {"id": 67628, "name": "Timbuktu"}]}]
