[{"c_id": 17, "name": "Acklins", "state_code": "AK", "cities": []}, {"c_id": 17, "name": "Acklins and Crooked Islands", "state_code": "AC", "cities": []}, {"c_id": 17, "name": "Berry Islands", "state_code": "BY", "cities": []}, {"c_id": 17, "name": "Bimini", "state_code": "BI", "cities": [{"id": 15686, "name": "Alice Town"}]}, {"c_id": 17, "name": "Black Point", "state_code": "BP", "cities": []}, {"c_id": 17, "name": "Cat Island", "state_code": "CI", "cities": [{"id": 15688, "name": "Arthur\u2019s Town"}]}, {"c_id": 17, "name": "Central Abaco", "state_code": "CO", "cities": [{"id": 15699, "name": "Marsh Harbour"}]}, {"c_id": 17, "name": "Central Andros", "state_code": "CS", "cities": []}, {"c_id": 17, "name": "Central Eleuthera", "state_code": "CE", "cities": []}, {"c_id": 17, "name": "Crooked Island", "state_code": "CK", "cities": [{"id": 15691, "name": "Colonel Hill"}]}, {"c_id": 17, "name": "East Grand Bahama", "state_code": "EG", "cities": [{"id": 15697, "name": "High Rock"}]}, {"c_id": 17, "name": "Exuma", "state_code": "EX", "cities": [{"id": 15696, "name": "George Town"}]}, {"c_id": 17, "name": "Freeport", "state_code": "FP", "cities": [{"id": 15695, "name": "Freeport"}, {"id": 15698, "name": "Lucaya"}]}, {"c_id": 17, "name": "Fresh Creek", "state_code": "FC", "cities": []}, {"c_id": 17, "name": "Governor's Harbour", "state_code": "GH", "cities": []}, {"c_id": 17, "name": "Grand Cay", "state_code": "GC", "cities": []}, {"c_id": 17, "name": "Green Turtle Cay", "state_code": "GT", "cities": []}, {"c_id": 17, "name": "Harbour Island", "state_code": "HI", "cities": [{"id": 15694, "name": "Dunmore Town"}]}, {"c_id": 17, "name": "High Rock", "state_code": "HR", "cities": []}, {"c_id": 17, "name": "Hope Town", "state_code": "HT", "cities": []}, {"c_id": 17, "name": "Inagua", "state_code": "IN", "cities": [{"id": 15700, "name": "Matthew Town"}]}, {"c_id": 17, "name": "Kemps Bay", "state_code": "KB", "cities": []}, {"c_id": 17, "name": "Long Island", "state_code": "LI", "cities": [{"id": 15689, "name": "Clarence Town"}]}, {"c_id": 17, "name": "Mangrove Cay", "state_code": "MC", "cities": []}, {"c_id": 17, "name": "Marsh Harbour", "state_code": "MH", "cities": []}, {"c_id": 17, "name": "Mayaguana District", "state_code": "MG", "cities": [{"id": 15685, "name": "Abraham\u2019s Bay"}]}, {"c_id": 17, "name": "New Providence", "state_code": "NP", "cities": [{"id": 143913, "name": "Nassau"}]}, {"c_id": 17, "name": "Nichollstown and Berry Islands", "state_code": "NB", "cities": []}, {"c_id": 17, "name": "North Abaco", "state_code": "NO", "cities": [{"id": 15692, "name": "Cooper\u2019s Town"}]}, {"c_id": 17, "name": "North Andros", "state_code": "NS", "cities": [{"id": 15687, "name": "Andros Town"}, {"id": 15702, "name": "San Andros"}]}, {"c_id": 17, "name": "North Eleuthera", "state_code": "NE", "cities": []}, {"c_id": 17, "name": "Ragged Island", "state_code": "RI", "cities": [{"id": 15693, "name": "Duncan Town"}]}, {"c_id": 17, "name": "Rock Sound", "state_code": "RS", "cities": []}, {"c_id": 17, "name": "Rum Cay District", "state_code": "RC", "cities": [{"id": 15701, "name": "Port Nelson"}]}, {"c_id": 17, "name": "San Salvador and Rum Cay", "state_code": "SR", "cities": []}, {"c_id": 17, "name": "San Salvador Island", "state_code": "SS", "cities": [{"id": 15690, "name": "Cockburn Town"}]}, {"c_id": 17, "name": "Sandy Point", "state_code": "SP", "cities": []}, {"c_id": 17, "name": "South Abaco", "state_code": "SO", "cities": []}, {"c_id": 17, "name": "South Andros", "state_code": "SA", "cities": []}, {"c_id": 17, "name": "South Eleuthera", "state_code": "SE", "cities": []}, {"c_id": 17, "name": "Spanish Wells", "state_code": "SW", "cities": [{"id": 15703, "name": "Spanish Wells"}]}, {"c_id": 17, "name": "West Grand Bahama", "state_code": "WG", "cities": [{"id": 15704, "name": "West End"}]}]
